{
  "entries":[
    {
      "name": "Pingu",
      "number": "02086876000",
      "id": 1
    },
    {
      "name": "Piplup",
      "number": "07066775792",
      "id": 2
    },
    {
      "name": "Wheezy",
      "number": "07830494624",
      "id": 3
    },
    {
      "name": "Tuxedosam",
      "number": "07750295291",
      "id": 4
    },
    {
      "name": "Tux",
      "number": "07027167775",
      "id": 5
    },
    {
      "name": "Pinga",
      "number": "07034452515",
      "id": 6
    }
  ]
}